pause/__init__.py
pause/cmd_pause.py
pause/pause.py
pauseinpython-0.0.2.dist-info/METADATA
pauseinpython-0.0.2.dist-info/WHEEL
pauseinpython-0.0.2.dist-info/top_level.txt
pauseinpython-0.0.2.dist-info/RECORD
