Metadata-Version: 2.4
Name: pauseinpython
Version: 0.0.2
Summary: 'pause' command in Python
